MANIFEST.in
README.md
setup.py
django_wmata_realtime_snapshot.egg-info/PKG-INFO
django_wmata_realtime_snapshot.egg-info/SOURCES.txt
django_wmata_realtime_snapshot.egg-info/dependency_links.txt
django_wmata_realtime_snapshot.egg-info/top_level.txt
wmata_realtime_snapshot/__init__.py
wmata_realtime_snapshot/realtime.py
wmata_realtime_snapshot/urls.py
wmata_realtime_snapshot/views.py