Metadata-Version: 1.1
Name: django-wmata-realtime-snapshot
Version: 0.2
Summary: A point-in-time mirror of Washington DC Metro's realtime train schedule
Home-page: https://github.com/m3brown/django-wmata-realtime-snapshot
Author: Michael Brown
Author-email: brown.3.mike@gmail.com
License: BSD License
Platform: UNKNOWN
Classifier: Environment :: Web Environment
Classifier: Framework :: Django
Classifier: Intended Audience :: Developers
Classifier: License :: OSI Approved :: BSD License
Classifier: Operating System :: OS Independent
Classifier: Programming Language :: Python
Classifier: Programming Language :: Python :: 2
Classifier: Topic :: Internet :: WWW/HTTP
